egegsignals
